lixtools/__init__.py
lixtools/atsas.py
lixtools/mailin.py
lixtools/modeling.py
lixtools/plant_tomo.py
lixtools/plate_label_template.html
lixtools/template_report.ipynb
lixtools/hdf/__init__.py
lixtools/hdf/an.py
lixtools/hdf/hplc.py
lixtools/hdf/scan.py
lixtools/hdf/scan0.py
lixtools/hdf/sol.py
lixtools/inst/ot2.py
lixtools/inst/ot2_gen_prot.py
lixtools/inst/webcam.py
lixtools/notebooks/__init__.py
lixtools/notebooks/generic.py
lixtools/notebooks/scanning.py
lixtools/notebooks/sol_hplc.py
lixtools/notebooks/sol_hplc_mcr.py
lixtools/notebooks/sol_static.py
lixtools/notebooks/subtract_buffer_mcr.py
lixtools-2023.1.23.0.dist-info/LICENSE
lixtools-2023.1.23.0.dist-info/METADATA
lixtools-2023.1.23.0.dist-info/WHEEL
lixtools-2023.1.23.0.dist-info/top_level.txt
lixtools-2023.1.23.0.dist-info/RECORD
