Metadata-Version: 2.1
Name: lixtools
Version: 2023.1.23.0
Summary: software tools for data collection/processing at LiX
Home-page: https://github.com/NSLS-II-LIX/lixtools
Author: Lin Yang
Author-email: lyang@bnl.gov
License: BSD-3-Clause
Keywords: x-ray scattering
Classifier: Intended Audience :: Science/Research
Classifier: Topic :: Scientific/Engineering :: Information Analysis
Classifier: Development Status :: 3 - Alpha
Classifier: Programming Language :: Python :: 3.6
Requires-Python: >=3.6
License-File: LICENSE
Requires-Dist: py4xs
Requires-Dist: numpy
Requires-Dist: pandas
Requires-Dist: scipy (>=1.6)
Requires-Dist: fast-histogram
Requires-Dist: python-barcode
Requires-Dist: matplotlib
Requires-Dist: pillow
Requires-Dist: openpyxl (>=3)
Requires-Dist: qrcode
